main.py
setup.py
uuss.egg-info/PKG-INFO
uuss.egg-info/SOURCES.txt
uuss.egg-info/dependency_links.txt
uuss.egg-info/requires.txt
uuss.egg-info/top_level.txt